README.md
setup.cfg
setup.py
EAMetatrader/__init__.py
EAMetatrader.egg-info/PKG-INFO
EAMetatrader.egg-info/SOURCES.txt
EAMetatrader.egg-info/dependency_links.txt
EAMetatrader.egg-info/requires.txt
EAMetatrader.egg-info/top_level.txt
EAMetatrader/Client/EAMT.py
EAMetatrader/Client/MtApi.dll
EAMetatrader/Client/Newtonsoft.Json.dll
EAMetatrader/Client/__init__.py
EAMetatrader/Enums/EnumObjects.py
EAMetatrader/Enums/__init__.py
EAMetatrader/Using/System.Drawing.dll
EAMetatrader/Using/WindowsBase.dll
EAMetatrader/Using/__init__.py
EAMetatrader/Using/using.py