Metadata-Version: 2.1
Name: EAMetatrader
Version: 1.0.4
Summary: Metatrader library for python
Home-page: https://github.com/EAScript/EAMT
Author: EAScript
Author-email: ehsanakbariea8@gmail.com
License: MIT
Download-URL: https://github.com/EAScript/EAMT/archive/refs/tags/1.0.4.tar.gz
Project-URL: Bug Tracker, https://github.com/EAScript/EAMT/issues
Keywords: EAMetatrader,Metatrader,Metatrader4,Metatrader5,python+metatrader,MtApi,mql4,mql5
Platform: UNKNOWN
Classifier: Development Status :: 3 - Alpha
Classifier: Intended Audience :: Developers
Classifier: Topic :: Software Development :: Build Tools
Classifier: License :: OSI Approved :: MIT License
Classifier: Programming Language :: Python :: 3
Classifier: Programming Language :: Python :: 3.4
Classifier: Programming Language :: Python :: 3.5
Classifier: Programming Language :: Python :: 3.6
Classifier: Programming Language :: Python :: 3.7
